{
  "posts": [
    {
      "id": 1,
      "title": "json-server",
      "author": "typicode"
    },
    {
      "id": 2,
      "title": "json-server",
      "author": "typicode"
    }
  ],
  "comments": [
    {
      "sum": "120",
      "category": "Sport",
      "bankAccount": "Tinkoff",
      "comment": "buying a pi ball",
      "id": 1
    },
    {
      "sum": "21",
      "category": "Sport",
      "bankAccount": "Tinkoff",
      "comment": "buy a tennis",
      "id": 2
    },
    {
      "sum": "1000",
      "category": "Dinner",
      "bankAccount": "Sber",
      "comment": "Soup Rassolnik",
      "id": 3
    },
    {
      "sum": "890",
      "category": "Dinner",
      "bankAccount": "Alfa",
      "comment": "Pizza",
      "id": 4
    },
    {
      "sum": "120",
      "category": "Relax",
      "bankAccount": "SPB",
      "comment": "SPA",
      "id": 5
    }
  ],
  "operations": [
    {
      "idBankAccount": "12345",
      "sum": "1000",
      "category": "Продукты",
      "comment": "",
      "id": 1682199874661
    },
    {
      "idBankAccount": "12345",
      "sum": "2000",
      "category": "Одежда",
      "comment": "",
      "id": 1682199881245
    },
    {
      "idBankAccount": "12345",
      "sum": "5000",
      "category": "Спорт",
      "comment": "",
      "id": 1682199889714
    },
    {
      "idBankAccount": "12345",
      "sum": "1234",
      "category": "Спорт",
      "comment": "",
      "id": 1682200360409
    },
    {
      "idBankAccount": "12345",
      "sum": "2345",
      "category": "Продукты",
      "comment": "",
      "id": 1682200369285
    },
    {
      "idBankAccount": "12345",
      "sum": "234",
      "category": "Одежда",
      "comment": "",
      "id": 1682200404823
    },
    {
      "idBankAccount": "12345",
      "sum": "100",
      "category": "Одежда",
      "comment": "покупка трусов",
      "id": 1684268405287
    },
    {
      "idBankAccount": "12345",
      "sum": "1000",
      "category": "Спорт",
      "comment": "цй",
      "id": 1684268420690
    },
    {
      "idBankAccount": "12345",
      "sum": "10000",
      "category": "Спорт",
      "comment": "CNaw",
      "id": 1684441704632
    }
  ]
}
